app_reviews_analysis/__init__.py
app_reviews_analysis/relation.py
app_reviews_analysis/reviewPretreate.py
app_reviews_analysis/timeSeriesPrediction.py
app_reviews_analysis/static/SentiStrength.jar
app_reviews_analysis/static/SentStrength_Data/BoosterWordList.txt
app_reviews_analysis/static/SentStrength_Data/EmoticonLookupTable.txt
app_reviews_analysis/static/SentStrength_Data/EmotionLookupTable.txt
app_reviews_analysis/static/SentStrength_Data/EnglishWordList.txt
app_reviews_analysis/static/SentStrength_Data/IdiomLookupTable.txt
app_reviews_analysis/static/SentStrength_Data/NegatingWordList.txt
app_reviews_analysis/static/SentStrength_Data/QuestionWords.txt
app_reviews_analysis/static/SentStrength_Data/SlangLookupTable.txt
app_reviews_analysis/static/sentiment/主张词语（英文）.txt
app_reviews_analysis/static/sentiment/正面情感词语（英文）.txt
app_reviews_analysis/static/sentiment/正面评价词语（英文）.txt
app_reviews_analysis/static/sentiment/程度级别词语（英文）.txt
app_reviews_analysis/static/sentiment/负面情感词语（英文）.txt
app_reviews_analysis/static/sentiment/负面评价词语（英文）.txt
app_reviews_analysis-0.0.4.dist-info/DESCRIPTION.rst
app_reviews_analysis-0.0.4.dist-info/METADATA
app_reviews_analysis-0.0.4.dist-info/RECORD
app_reviews_analysis-0.0.4.dist-info/WHEEL
app_reviews_analysis-0.0.4.dist-info/metadata.json
app_reviews_analysis-0.0.4.dist-info/top_level.txt
