Metadata-Version: 2.0
Name: app-reviews-analysis
Version: 0.0.4
Summary: This library, based on NLTK library and sentience.jar package, is designed to help analyze App comment data, and can implement comment feature extraction, comment emotion analysis, comment star and comment emotion correlation analysis, and comment emotion score prediction
Home-page: UNKNOWN
Author: lailai
Author-email: 739198457@qq.com
License: UNKNOWN
Platform: UNKNOWN
Classifier: Development Status :: 5 - Production/Stable
Classifier: Intended Audience :: Developers
Classifier: Natural Language :: English
Classifier: License :: OSI Approved :: MIT License
Classifier: Programming Language :: Python
Classifier: Programming Language :: Python :: 3
Classifier: Programming Language :: Python :: 3.4
Classifier: Programming Language :: Python :: 3.5
Classifier: Programming Language :: Python :: 3.6
Classifier: Programming Language :: Python :: 3.7
Classifier: Programming Language :: Python :: Implementation :: CPython
Classifier: Programming Language :: Python :: Implementation :: PyPy
Requires-Python: >=3.0, !=3.0.*, !=3.1.*, !=3.2.*, !=3.3*
Requires-Dist: emoji (==0.5.1)
Requires-Dist: gensim (==3.4.0)
Requires-Dist: langid (==1.1.6)
Requires-Dist: nltk (>=3.4)
Requires-Dist: pandas (>=0.23.4)
Requires-Dist: seaborn (==0.9.0)
